[
  {
    "eid": "940c24f9c3",
    "company": "Кременчуцьке КАТП 1628",
    "name": "МАЗ-555102 ВІ 9639 ВК",
    "type": "SP",
    "lat": 49.0965483333333,
    "lng": 33.4355316666667,
    "modTs": 1603890872000,
    "speed": 0
  },
  {
    "eid": "99215d28f1",
    "company": "Кременчуцьке КАТП 1628",
    "name": "МАЗ-555102 ВІ 9640 ВК",
    "type": "SP",
    "lat": 49.0715883333333,
    "lng": 33.4171166666667,
    "modTs": 1603890996000,
    "speed": 0
  },
  {
    "eid": "e530345334",
    "company": "Кременчуцьке КАТП 1628",
    "name": "КрАЗ-5401С2 BI 8983 CI",
    "type": "SP",
    "lat": 49.078295,
    "lng": 33.4106366666667,
    "modTs": 1603890254000,
    "speed": 0
  },
  {
    "eid": "96c0b806d3",
    "company": "Кременчуцьке КАТП 1628",
    "name": "КрАЗ-250 BI 8186 BM",
    "type": "SP",
    "lat": 48.9996416666667,
    "lng": 33.427825,
    "modTs": 1603891026000,
    "speed": 9
  },
  {
    "eid": "217d971fa8",
    "company": "Кременчуцьке КАТП 1628",
    "name": "КрАЗ-6510 BI 1896 BT",
    "type": "SP",
    "lat": 49.0004233333333,
    "lng": 33.426195,
    "modTs": 1603887004000,
    "speed": 0
  },
  {
    "eid": "97b1cd8719",
    "company": "Кременчуцьке КАТП 1628",
    "name": "КрАЗ-256Б1 4342 ПОТ",
    "type": "SP",
    "lat": 49.0784933333333,
    "lng": 33.4106733333333,
    "modTs": 1603890355000,
    "speed": 0
  },
  {
    "eid": "464b58cba3",
    "company": "Кременчуцьке КАТП 1628",
    "name": "ВЛІВ медіум В 18-20 KR КрАЗ-5401H2 ВІ 8572 СМ",
    "type": "SW",
    "lat": 49.0720270666667,
    "lng": 33.4087183333333,
    "modTs": 1603890751000,
    "speed": 0
  },
  {
    "eid": "8330d0e0fa",
    "company": "Кременчуцьке КАТП 1628",
    "name": "ЕО-2628 9108 ПЛ",
    "type": "TR",
    "lat": 49.0774616666667,
    "lng": 33.4106383333333,
    "modTs": 1603890097000,
    "speed": 0
  },
  {
    "eid": "0933f694a9",
    "company": "Кременчуцьке КАТП 1628",
    "name": "Борекс-2101 28667 НО",
    "type": "TR",
    "lat": 49.14556,
    "lng": 33.43722,
    "modTs": 1603890594000,
    "speed": 0
  },
  {
    "eid": "4306054bfb",
    "company": "Кременчуцьке КАТП 1628",
    "name": "ЮМЗ-6АКЛ 28782 НО",
    "type": "TR",
    "lat": 49.0626816666667,
    "lng": 33.419245,
    "modTs": 1603872056000,
    "speed": 4
  },
  {
    "eid": "57ff456b04",
    "company": "Кременчуцьке КАТП 1628",
    "name": "KO-707 3562 ПЛ",
    "type": "TR",
    "lat": 49.0857083333333,
    "lng": 33.4249233333333,
    "modTs": 1603891008000,
    "speed": 0
  },
  {
    "eid": "97fac94793",
    "company": "Кременчуцьке КАТП 1628",
    "name": "Білорус-82.1 25847 BI",
    "type": "TR",
    "lat": 49.0966882333333,
    "lng": 33.4354483333333,
    "modTs": 1603891021000,
    "speed": 1
  },
  {
    "eid": "6f35bdc1f5",
    "company": "Кременчуцьке КАТП 1628",
    "name": "Білорус-82.1 25836 BI",
    "type": "TR",
    "lat": 49.13594,
    "lng": 33.44791,
    "modTs": 1603891125000,
    "speed": 6
  },
  {
    "eid": "df478cdc92",
    "company": "КПС ШРБУ",
    "name": "КрАЗ 4661 ПОТ",
    "type": "SW",
    "lat": 49.0235150666667,
    "lng": 33.462955,
    "modTs": 1603890660000,
    "speed": 0
  },
  {
    "eid": "e40e277fc2",
    "company": "КПС ШРБУ",
    "name": "КрАЗ ВІ 4478 АС",
    "type": "SW",
    "lat": 49.0897583333333,
    "lng": 33.403815,
    "modTs": 1603891091000,
    "speed": 24
  },
  {
    "eid": "8151a00148",
    "company": "КПС ШРБУ",
    "name": "КрАЗ 4209 ПОТ",
    "type": "SW",
    "lat": 49.07056,
    "lng": 33.4076483333333,
    "modTs": 1603890718000,
    "speed": 0
  },
  {
    "eid": "0e02958d26",
    "company": "КПС ШРБУ",
    "name": "КрАЗ 019-17 СН",
    "type": "SW",
    "lat": 49.082875,
    "lng": 33.443885,
    "modTs": 1603891093000,
    "speed": 28
  },
  {
    "eid": "a23bed5d3c",
    "company": "КПС ШРБУ",
    "name": "КрАЗ 6080 ПОС",
    "type": "SW",
    "lat": 49.09592,
    "lng": 33.4026866666667,
    "modTs": 1603891081000,
    "speed": 0
  },
  {
    "eid": "d518797b32",
    "company": "КПС ШРБУ",
    "name": "КрАЗ 4407 ПОУ",
    "type": "SW",
    "lat": 49.1274883333333,
    "lng": 33.4215066666667,
    "modTs": 1603891096000,
    "speed": 35
  },
  {
    "eid": "11e0e847f0",
    "company": "КПС ШРБУ",
    "name": "МАЗ ВІ 2946 СМ",
    "type": "SW",
    "lat": 49.0792166,
    "lng": 33.4124333,
    "modTs": 1603891099000,
    "speed": 0
  },
  {
    "eid": "7bed0aa6f8",
    "company": "КПС ШРБУ",
    "name": "МАЗ ВІ 2948 СМ",
    "type": "SW",
    "lat": 49.0791333,
    "lng": 33.4123833,
    "modTs": 1603891130000,
    "speed": 0
  },
  {
    "eid": "e86fcc3322",
    "company": "КПС ШРБУ",
    "name": "МАЗ ВІ 4109 СН",
    "type": "SW",
    "lat": 49.07875,
    "lng": 33.4121499,
    "modTs": 1603891034000,
    "speed": 0
  },
  {
    "eid": "3d0de47d94",
    "company": "КПС ШРБУ",
    "name": "Грейдер 24672 НО",
    "type": "TR",
    "lat": 49.07039,
    "lng": 33.40785,
    "modTs": 1603891092000,
    "speed": 0
  },
  {
    "eid": "c3166dca59",
    "company": "КПС ШРБУ",
    "name": "JCB 10689 BI",
    "type": "TR",
    "lat": 49.067925,
    "lng": 33.403685,
    "modTs": 1603891123000,
    "speed": 3
  },
  {
    "eid": "3492f7e449",
    "company": "Благоустрій Кременчука",
    "name": "КрАЗ BI 5360 BK",
    "type": "SW",
    "lat": 49.0879933333333,
    "lng": 33.4342883333333,
    "modTs": 1603890615000,
    "speed": 0
  },
  {
    "eid": "362813961e",
    "company": "Благоустрій Кременчука",
    "name": "15698 HO",
    "type": "TR",
    "lat": 49.0604816666667,
    "lng": 33.4154466666667,
    "modTs": 1603890349000,
    "speed": 0
  },
  {
    "eid": "3815101052",
    "company": "Благоустрій Кременчука",
    "name": "Bobcat 15646 BI",
    "type": "TR",
    "lat": 49.0668483333333,
    "lng": 33.4090466666667,
    "modTs": 1603890331000,
    "speed": 0
  },
  {
    "eid": "aefc21c7cc",
    "company": "Благоустрій Кременчука",
    "name": "Bobcat 14164 BI",
    "type": "TR",
    "lat": 50.308645,
    "lng": 30.828485,
    "modTs": 1603889555000,
    "speed": 0
  },
  {
    "eid": "ff5a3afd29",
    "company": "Благоустрій Кременчука",
    "name": "02832 HO",
    "type": "TR",
    "lat": 49.077415,
    "lng": 33.41139,
    "modTs": 1603890179000,
    "speed": 0
  },
  {
    "eid": "5ed06caeba",
    "company": "Благоустрій Кременчука",
    "name": "15680 HO",
    "type": "TR",
    "lat": 49.0796866666667,
    "lng": 33.4078733333333,
    "modTs": 1603890596000,
    "speed": 0
  },
  {
    "eid": "dc9fe3965b",
    "company": "Благоустрій Кременчука",
    "name": "Foton-1054 1",
    "type": "TR",
    "lat": 49.07177,
    "lng": 33.4056966666667,
    "modTs": 1603890710000,
    "speed": 0
  },
  {
    "eid": "737b91e9ad",
    "company": "Благоустрій Кременчука",
    "name": "Foton-1054 2",
    "type": "TR",
    "lat": 49.0286533333333,
    "lng": 33.435805,
    "modTs": 1603891127000,
    "speed": 2
  },
  {
    "eid": "399751fc0e",
    "company": "Благоустрій Кременчука",
    "name": "Foton-504 25024 BI",
    "type": "TR",
    "lat": 49.0359573,
    "lng": 33.4436645,
    "modTs": 1603891035000,
    "speed": 0
  },
  {
    "eid": "ccbcb61e6d",
    "company": "Благоустрій Кременчука",
    "name": "Foton-504 25025 BI",
    "type": "TR",
    "lat": 49.0778312,
    "lng": 33.4102172,
    "modTs": 1603881781000,
    "speed": 7
  },
  {
    "eid": "bd08140757",
    "company": "Благоустрій Кременчука",
    "name": "Foton-504 25026 BI",
    "type": "TR",
    "lat": 49.0289001,
    "lng": 33.4364242,
    "modTs": 1603890841000,
    "speed": 0
  },
  {
    "eid": "5385777b06",
    "company": "Благоустрій Кременчука",
    "name": "Foton-504 25027 BI",
    "type": "TR",
    "lat": 49.0717277,
    "lng": 33.405651,
    "modTs": 1603891111000,
    "speed": 0
  },
  {
    "eid": "9837712c15",
    "company": "КРЕМЕНЧУКВОДОКАНАЛ",
    "name": "КрАЗ 147-89 СН",
    "type": "SW",
    "lat": 49.0850033333333,
    "lng": 33.4293633333333,
    "modTs": 1603891069000,
    "speed": 0
  },
  {
    "eid": "4201a11631",
    "company": "КРЕМЕНЧУКВОДОКАНАЛ",
    "name": "КрАЗ 124-14 СН",
    "type": "SW",
    "lat": 49.0854833333333,
    "lng": 33.4294166666667,
    "modTs": 1603872098000,
    "speed": 18
  },
  {
    "eid": "c44fe73b9f",
    "company": "КРЕМЕНЧУКВОДОКАНАЛ",
    "name": "Борекс 245-48 НО",
    "type": "TR",
    "lat": 49.0847333333333,
    "lng": 33.429405,
    "modTs": 1603891105000,
    "speed": 0
  },
  {
    "eid": "53619d5dc1",
    "company": "КРЕМЕНЧУКВОДОКАНАЛ",
    "name": "JCB",
    "type": "TR",
    "lat": 49.0845366666667,
    "lng": 33.4289266666667,
    "modTs": 1603891070000,
    "speed": 0
  }
]
